xhs_bailian_mcp_server_v1/__init__.py
xhs_bailian_mcp_server_v1/server.py
xhs_bailian_mcp_server_v1-0.1.0.dist-info/WHEEL
xhs_bailian_mcp_server_v1-0.1.0.dist-info/entry_points.txt
xhs_bailian_mcp_server_v1-0.1.0.dist-info/METADATA
xhs_bailian_mcp_server_v1-0.1.0.dist-info/RECORD
