Metadata-Version: 2.3
Name: xhs-bailian-mcp-server-v1
Version: 0.1.0
Summary: Add your description here
Author: lvwenxiang
Author-email: lvwenxiang <lvwenxiang@microconnect.com>
Requires-Dist: bs4>=0.0.2
Requires-Dist: dashscope>=1.24.1
Requires-Dist: dotenv>=0.9.9
Requires-Dist: httpx>=0.28.1
Requires-Dist: mcp[cli]>=1.12.3
Requires-Python: >=3.10
